braketlab/__init__.py
braketlab/animate.py
braketlab/basisbank.py
braketlab/braketlab.py
braketlab/core.py
braketlab/harmonic_oscillator.py
braketlab/hydrogen.py
braketlab/metropolis_hastings.py
braketlab/real_solid_harmonics.py
braketlab/solid_harmonics.py
BraketLab-1.78.dist-info/LICENCE
BraketLab-1.78.dist-info/METADATA
BraketLab-1.78.dist-info/WHEEL
BraketLab-1.78.dist-info/top_level.txt
BraketLab-1.78.dist-info/RECORD
