Metadata-Version: 2.1
Name: BraketLab
Version: 1.78
Summary: Educational tool for learning quantum theory with Jupyter Notebooks
Home-page: https://github.uio.no/audunsh/braketlab
Author: Audun Skau Hansen
Author-email: a.s.hansen@kjemi.uio.no
Classifier: Programming Language :: Python :: 3
Classifier: License :: OSI Approved :: MIT License
Classifier: Operating System :: OS Independent
License-File: LICENCE
Requires-Dist: sympy
Requires-Dist: numba
Requires-Dist: evince
Requires-Dist: bubblebox
